README.txt
setup.py
src/nous/__init__.py
src/nous.pystat.egg-info/PKG-INFO
src/nous.pystat.egg-info/SOURCES.txt
src/nous.pystat.egg-info/dependency_links.txt
src/nous.pystat.egg-info/not-zip-safe
src/nous.pystat.egg-info/requires.txt
src/nous.pystat.egg-info/top_level.txt
src/nous/pystat/__init__.py
src/nous/pystat/statprof.py
src/nous/pystat/stats.py
src/nous/pystat/zodbprof.py