Metadata-Version: 1.0
Name: nous.pystat
Version: 0.1
Summary: Utilities to collect interesting stats about your code.
Home-page: http://github.com/Ignas/nous.pystat/
Author: Ignas Mikalajunas
Author-email: ignas@nous.lt
License: GPL
Platform: UNKNOWN
Classifier: Development Status :: 3 - Alpha
Classifier: Intended Audience :: Developers
Classifier: License :: OSI Approved :: GNU General Public License (GPL)
Classifier: Programming Language :: Python
